somweb/__init__.py
somweb/__version__.py
somweb/client.py
somweb/const.py
somweb/httpclient.py
somweb/models.py
somweb-1.3.2.dist-info/LICENSE
somweb-1.3.2.dist-info/METADATA
somweb-1.3.2.dist-info/WHEEL
somweb-1.3.2.dist-info/top_level.txt
somweb-1.3.2.dist-info/RECORD
