Metadata-Version: 2.1
Name: somweb
Version: 1.3.2
Summary: SOMweb client. Open/close Garage doors produced by SOMMER (base+/pro+/tiga/tiga+/barrier systems)
Home-page: https://github.com/taarskog/pysomweb
Download-URL: https://github.com/taarskog/pysomweb/archive/v1.3.2.tar.gz
Author: Trond Aarskog
Author-email: somweb@heiigjen.com
License: MIT
Keywords: sommer,SOMweb,garage door,home assistant,home automation,heiigjen
Classifier: Development Status :: 3 - Alpha
Classifier: License :: OSI Approved :: MIT License
Classifier: Intended Audience :: Developers
Classifier: Programming Language :: Python
Classifier: Programming Language :: Python :: 3
Classifier: Programming Language :: Python :: 3.10
Classifier: Operating System :: OS Independent
Classifier: Topic :: Home Automation
Classifier: Topic :: Software Development :: Libraries :: Python Modules
Requires-Python: >=3.6.0
License-File: LICENSE
Requires-Dist: requests
Requires-Dist: aiohttp
